sxscatalog/__about__.py
sxscatalog/__init__.py
sxscatalog/metadata/__init__.py
sxscatalog/metadata/metadata.py
sxscatalog/metadata/metric.py
sxscatalog/simulations/__init__.py
sxscatalog/simulations/local.py
sxscatalog/simulations/simulations.py
sxscatalog/utilities/__init__.py
sxscatalog/utilities/downloads.py
sxscatalog/utilities/files.py
sxscatalog/utilities/string_converters.py
sxscatalog/utilities/sxs_directories.py
sxscatalog/utilities/sxs_identifiers.py
sxscatalog-3.0.18.dist-info/METADATA
sxscatalog-3.0.18.dist-info/WHEEL
sxscatalog-3.0.18.dist-info/licenses/LICENSE.txt
sxscatalog-3.0.18.dist-info/RECORD
