Metadata-Version: 2.4
Name: sxscatalog
Version: 3.0.18
Summary: Interface to the catalog of SXS simulations
Project-URL: Documentation, https://github.com/sxs-collaboration/sxscatalog#readme
Project-URL: Issues, https://github.com/sxs-collaboration/sxscatalog/issues
Project-URL: Source, https://github.com/sxs-collaboration/sxscatalog
Author-email: Mike Boyle <michael.oliver.boyle@gmail.com>
License-Expression: MIT
License-File: LICENSE.txt
Classifier: Development Status :: 4 - Beta
Classifier: Programming Language :: Python
Classifier: Programming Language :: Python :: 3.8
Classifier: Programming Language :: Python :: 3.9
Classifier: Programming Language :: Python :: 3.10
Classifier: Programming Language :: Python :: 3.11
Classifier: Programming Language :: Python :: 3.12
Classifier: Programming Language :: Python :: Implementation :: CPython
Classifier: Programming Language :: Python :: Implementation :: PyPy
Requires-Python: >=3.8
Requires-Dist: numpy
Requires-Dist: packaging
Requires-Dist: pandas
Requires-Dist: requests
Requires-Dist: tqdm
